ddd/__init__.py
ddd/aggregates.py
ddd/infra.py
ddd/services.py
ddd/values.py
ddd_core-0.1.3.dist-info/METADATA
ddd_core-0.1.3.dist-info/WHEEL
ddd_core-0.1.3.dist-info/RECORD
