Metadata-Version: 2.1
Name: ddd-core
Version: 0.1.3
Summary: Library for programming application layer using Domain Driven Design
License: LGPL
Author: Salvador Ruiz
Author-email: sruiz@indoorclima.com
Requires-Python: >=3.11,<4.0
Classifier: License :: Other/Proprietary License
Classifier: Programming Language :: Python :: 3
Classifier: Programming Language :: Python :: 3.11
